spark_ml_utils/LogisticRegressionModel_util.py
spark_ml_utils/__init__.py
spark_ml_utils/pipeline_util.py
spark_ml_utils-0.0.3.dist-info/LICENSE.txt
spark_ml_utils-0.0.3.dist-info/METADATA
spark_ml_utils-0.0.3.dist-info/WHEEL
spark_ml_utils-0.0.3.dist-info/top_level.txt
spark_ml_utils-0.0.3.dist-info/RECORD
